shaderc_rs_py-0.2.2.dist-info/METADATA
shaderc_rs_py-0.2.2.dist-info/WHEEL
shaderc_rs_py-0.2.2.dist-info/licenses/LICENSE
shadercrs/enums.py
shadercrs/__init__.py
shadercrs/shadercrs.pyd
shaderc_rs_py-0.2.2.dist-info/RECORD
