Metadata-Version: 2.4
Name: shaderc-rs-py
Version: 0.2.2
Classifier: Programming Language :: Rust
Classifier: Programming Language :: Python :: Implementation :: CPython
Classifier: Programming Language :: Python :: Implementation :: PyPy
Requires-Dist: pyside6>=6.6.3.1
Requires-Dist: ruff>=0.9.2
Requires-Dist: wgpu>=0.18.1
Requires-Dist: pytest ; extra == 'tests'
Provides-Extra: tests
License-File: LICENSE
Requires-Python: >=3.8
